{
  "name": "sppCap",
  "version": "1.0.0",
  "description": "Generated by cds-services-archetype",
  "license": "ISC",
  "repository": "<Add your repository here>",
  "scripts": {
    "deploy": "cds deploy --to hana:hana-hdi-shared-srv --no-save",
    "deploy-un": "cds deploy --to hana:hana-hdi-shared-srv --no-save --auto-undeploy"
  },
  "dependencies": {
    "@sap/cds": "^4.6.5",
    "@sap/cds-dk": "^3.5.1",
    "@sap/cds-mtx": "^1.1.5",
    "@sap/hana-client": "^2.7.26",
    "@sap/hdi-deploy": "^4.0.5"
  },
  "cds": {
    "hana": {
      "deploy-format": "hdbtable"
    },
    "requires": {
      "db": {
        "kind": "hana"
      },
      "uaa": {
        "kind": "xsuaa"
      }
    }
  },
  "devDependencies": {
    "@sap/approuter": "8.1.x",
    "@sap/eslint-plugin-ui5-jsdocs": "2.0.x",
    "@sap/html5-repo-mock": "1.5.x",
    "@sap/ui5-builder-webide-extension": "^1.1.5",
    "@sapui5/ts-types": "1.71.x",
    "@ui5/cli": "2.2.6",
    "bestzip": "^2.2.0",
    "eslint": "5.16.x",
    "rimraf": "3.0.2",
    "sqlite3": "^5.0.2"
  },
  "ui5": {
    "dependencies": [
      "@sap/ui5-builder-webide-extension"
    ]
  }
}

